{
 "type": "FeatureCollection",
 "features": [
  {
   "type": "Feature",
   "id": "node/6590934172",
   "properties": {
    "access": "customer",
    "description": "Access on Level -1 of the car park, adjacent to the disabled parking area. Standard and powered wheelchairs, as well as powered scooters.",
    "name": "intu Chapelfield Shopmobility Centre",
    "operator": "intu Chapelfield",
    "phone": "+44 1603 753350",
    "shop": "mobility",
    "website": "https://intu.co.uk/chapelfield/services/shopmobility",
    "wheelchair": "yes",
    "id": "node/6590934172",
    "mapFeature": {
     "caption": "intu Chapelfield Shopmobility Centre",
     "allowPopup": true,
     "location": "  \n  <br />\n  Access on Level -1 of the car park, adjacent to the disabled parking area. Standard and powered wheelchairs, as well as powered scooters.<br />\n  Wheelchair accessible \n  ",
     "layers": [
      "around"
     ]
    }
   },
   "geometry": {
    "type": "Point",
    "coordinates": [
     1.2900891,
     52.6261718
    ]
   }
  }
 ]
}